phantasia/__init__.py
phantasia-0.0.1.dist-info/METADATA
phantasia-0.0.1.dist-info/WHEEL
phantasia-0.0.1.dist-info/top_level.txt
phantasia-0.0.1.dist-info/RECORD
