Metadata-Version: 2.1
Name: phantasia
Version: 0.0.1
Summary: Phantasi
Author-email: Richard Kent <qpotizo@gmail.com>
Project-URL: Homepage, https://github.com/sparverius/phantasia
Project-URL: Bug Tracker, https://github.com/sparverius/phantasia/issues
